aayushserv/__init__.py
aayushserv/server.py
aayushserv-0.0.1.dist-info/METADATA
aayushserv-0.0.1.dist-info/WHEEL
aayushserv-0.0.1.dist-info/top_level.txt
aayushserv-0.0.1.dist-info/RECORD
