Metadata-Version: 2.4
Name: aayushserv
Version: 0.0.1
Summary: Super simple local server for HTML login forms
Home-page: https://github.com/Aayushbohora
Author: Aayush
Classifier: Programming Language :: Python :: 3
Classifier: Operating System :: OS Independent
Requires-Python: >=3.8
Dynamic: author
Dynamic: classifier
Dynamic: home-page
Dynamic: requires-python
Dynamic: summary
